viewererer/__init__.cp310-win_amd64.pyd
viewererer/__init__.py
viewererer/viewererer-config.json
viewererer-0.1.0.dist-info/METADATA
viewererer-0.1.0.dist-info/WHEEL
viewererer-0.1.0.dist-info/entry_points.txt
viewererer-0.1.0.dist-info/top_level.txt
viewererer-0.1.0.dist-info/RECORD
