Metadata-Version: 2.1
Name: viewererer
Version: 0.1.0
Summary: viewererer
Home-page: http://none.com
Author: syz
Author-email: none@mail.com
